fashionstar_uservo_sdk-0.0.2.dist-info/licenses/LICENSE.txt
uservo_sdk/__init__.py
uservo_sdk/uservo.py
fashionstar_uservo_sdk-0.0.2.dist-info/METADATA
fashionstar_uservo_sdk-0.0.2.dist-info/WHEEL
fashionstar_uservo_sdk-0.0.2.dist-info/top_level.txt
fashionstar_uservo_sdk-0.0.2.dist-info/RECORD
