Metadata-Version: 2.4
Name: fashionstar-uservo-sdk
Version: 0.0.2
Summary: A UservoSDK package
Author: Welt
Author-email: 1994524450@qq.com
Classifier: Programming Language :: Python :: 3
Classifier: License :: OSI Approved :: MIT License
Classifier: Operating System :: OS Independent
Requires-Python: >=3.6
License-File: LICENSE.txt
Dynamic: author
Dynamic: author-email
Dynamic: classifier
Dynamic: description-content-type
Dynamic: license-file
Dynamic: requires-python
Dynamic: summary
